[
  {
    "Name": "Soft",
    "FemaleBreastStrength": 0.50,
    "FemaleButtStrength": 0.3,
    "FemaleThighStrength": 0.25,
    "FemaleBellyStrength": 0.2,
    "MaleButtStrength": 0.3,
    "MaleGroinStrength": 0.3,
    "MaleThighStrength": 0.25,
    "MaleBellyStrength": 0.2,
    "HairStrength": 0.35,
    "RagdollKnockbackStrength": 1.0,
    "MonsterArchetypeStrength": 0.35,
    "FarmAnimalPhysicsStrength": 0.3,
    "EnvironmentalPhysicsStrength": 0.3,
    "DebrisPhysicsStrength": 0.35
  },
  {
    "Name": "Default",
    "FemaleBreastStrength": 0.75,
    "FemaleButtStrength": 0.5,
    "FemaleThighStrength": 0.4,
    "FemaleBellyStrength": 0.3,
    "MaleButtStrength": 0.45,
    "MaleGroinStrength": 0.45,
    "MaleThighStrength": 0.35,
    "MaleBellyStrength": 0.25,
    "HairStrength": 0.55,
    "RagdollKnockbackStrength": 1.5,
    "MonsterArchetypeStrength": 0.55,
    "FarmAnimalPhysicsStrength": 0.45,
    "EnvironmentalPhysicsStrength": 0.5,
    "DebrisPhysicsStrength": 0.65
  },
  {
    "Name": "High",
    "FemaleBreastStrength": 1.10,
    "FemaleButtStrength": 0.8,
    "FemaleThighStrength": 0.65,
    "FemaleBellyStrength": 0.45,
    "MaleButtStrength": 0.75,
    "MaleGroinStrength": 0.75,
    "MaleThighStrength": 0.55,
    "MaleBellyStrength": 0.4,
    "HairStrength": 0.85,
    "RagdollKnockbackStrength": 2.5,
    "MonsterArchetypeStrength": 0.9,
    "FarmAnimalPhysicsStrength": 0.75,
    "EnvironmentalPhysicsStrength": 0.9,
    "DebrisPhysicsStrength": 1.1
  },
  {
    "Name": "ExtraBouncy",
    "FemaleBreastStrength": 1.85,
    "FemaleButtStrength": 1.60,
    "FemaleThighStrength": 1.20,
    "FemaleBellyStrength": 0.90,
    "MaleButtStrength": 1.40,
    "MaleGroinStrength": 1.40,
    "MaleThighStrength": 1.00,
    "MaleBellyStrength": 0.75,
    "HairStrength": 1.60,
    "RagdollKnockbackStrength": 3.5,
    "MonsterArchetypeStrength": 1.60,
    "FarmAnimalPhysicsStrength": 1.40,
    "EnvironmentalPhysicsStrength": 1.60,
    "DebrisPhysicsStrength": 1.80
  }
]
